__init__.py
mcmd.py
mcmd-1.0.1.dist-info/LICENSE
mcmd-1.0.1.dist-info/METADATA
mcmd-1.0.1.dist-info/WHEEL
mcmd-1.0.1.dist-info/top_level.txt
mcmd-1.0.1.dist-info/RECORD
