Metadata-Version: 2.1
Name: mcmd
Version: 1.0.1
Summary: Multi-view Classification framework based on Consensus Matrix Decomposition developed by Shubham Sharma at QUT
Author-email: Shubham Sharma <s55.sharma@hdr.qut.edu.au>
Project-URL: Homepage, https://github.com/ashishbhaskar/MCMD
Project-URL: Issues, https://github.com/ashishbhaskar/MCMD/issues
Classifier: Programming Language :: Python :: 3
Classifier: License :: OSI Approved :: MIT License
Classifier: Operating System :: OS Independent
Requires-Python: >=3.10
License-File: LICENSE
Requires-Dist: numpy
Requires-Dist: pandas
Requires-Dist: matplotlib
Requires-Dist: seaborn
Requires-Dist: tqdm
